{"DP": {"NORMAL": {"timestamps": [], "history": {}, "best": {"clear_type": {"value": "NO PLAY", "timestamp": null, "options": null}, "score": {"value": 0, "timestamp": null, "options": null}}}, "LEGGENDARIA": {"timestamps": ["20251227-163156"], "history": {"20251227-163156": {"clear_type": {"value": "FAILED", "new": true}, "dj_level": {"value": "B", "new": true}, "score": {"value": 2204, "new": true}, "miss_count": {"value": 143, "new": true}, "options": {"arrange": null, "flip": null, "assist": null, "battle": false, "special": false}, "playspeed": null}}, "best": {"latest": "20251227-163156", "clear_type": {"value": "FAILED", "timestamp": "20251227-163156", "options": {"arrange": null, "flip": null, "assist": null, "battle": false, "special": false}}, "dj_level": {"value": "B", "timestamp": "20251227-163156", "options": {"arrange": null, "flip": null, "assist": null, "battle": false, "special": false}}, "score": {"value": 2204, "timestamp": "20251227-163156", "options": {"arrange": null, "flip": null, "assist": null, "battle": false, "special": false}}, "miss_count": {"value": 143, "timestamp": "20251227-163156", "options": {"arrange": null, "flip": null, "assist": null, "battle": false, "special": false}}}, "notes": 1834, "latest": {"timestamp": "20251227-163156", "clear_type": {"value": "FAILED", "new": true}, "dj_level": {"value": "B", "new": true}, "score": {"value": 2204, "new": true}, "miss_count": {"value": 143, "new": true}, "options": {"arrange": null, "flip": null, "assist": null, "battle": false, "special": false}, "playspeed": null}, "achievement": {"fixed": {"clear_type": "FAILED", "dj_level": "B"}, "S-RANDOM": {"clear_type": null, "dj_level": null}, "fromhistoriesgenerate_lastversion": "0.20.0"}}, "ANOTHER": {"timestamps": [], "history": {}, "best": {"clear_type": {"value": "CLEAR", "timestamp": null, "options": null}, "dj_level": {"value": "A", "timestamp": null, "options": null}, "score": {"value": 1722, "timestamp": null, "options": null}, "miss_count": {"value": 66, "timestamp": null, "options": null}}}}}