{"DP": {"HYPER": {"timestamps": ["20251218-233626"], "history": {"20251218-233626": {"clear_type": {"value": "EXH-CLEAR", "new": true}, "dj_level": {"value": "AA", "new": true}, "score": {"value": 1634, "new": true}, "miss_count": {"value": 12, "new": true}, "options": {"arrange": null, "flip": null, "assist": null, "battle": false, "special": false}, "playspeed": null}}, "best": {"latest": "20251218-233626", "clear_type": {"value": "EXH-CLEAR", "timestamp": "20251218-233626", "options": {"arrange": null, "flip": null, "assist": null, "battle": false, "special": false}}, "dj_level": {"value": "AA", "timestamp": "20251218-233626", "options": {"arrange": null, "flip": null, "assist": null, "battle": false, "special": false}}, "score": {"value": 1634, "timestamp": "20251218-233626", "options": {"arrange": null, "flip": null, "assist": null, "battle": false, "special": false}}, "miss_count": {"value": 12, "timestamp": "20251218-233626", "options": {"arrange": null, "flip": null, "assist": null, "battle": false, "special": false}}}, "notes": 1038, "latest": {"timestamp": "20251218-233626", "clear_type": {"value": "EXH-CLEAR", "new": true}, "dj_level": {"value": "AA", "new": true}, "score": {"value": 1634, "new": true}, "miss_count": {"value": 12, "new": true}, "options": {"arrange": null, "flip": null, "assist": null, "battle": false, "special": false}, "playspeed": null}, "achievement": {"fixed": {"clear_type": "EXH-CLEAR", "dj_level": "AA"}, "S-RANDOM": {"clear_type": null, "dj_level": null}, "fromhistoriesgenerate_lastversion": "0.20.0"}}, "NORMAL": {"timestamps": ["20260226-002005"], "history": {"20260226-002005": {"clear_type": {"value": "EXH-CLEAR", "new": true}, "dj_level": {"value": "AA", "new": true}, "score": {"value": 1170, "new": true}, "miss_count": {"value": 10, "new": true}, "options": {"arrange": null, "flip": null, "assist": null, "battle": false, "special": false}, "playspeed": null}}, "best": {"latest": "20260226-002005", "clear_type": {"value": "EXH-CLEAR", "timestamp": "20260226-002005", "options": {"arrange": null, "flip": null, "assist": null, "battle": false, "special": false}}, "dj_level": {"value": "AA", "timestamp": "20260226-002005", "options": {"arrange": null, "flip": null, "assist": null, "battle": false, "special": false}}, "score": {"value": 1170, "timestamp": "20260226-002005", "options": {"arrange": null, "flip": null, "assist": null, "battle": false, "special": false}}, "miss_count": {"value": 10, "timestamp": "20260226-002005", "options": {"arrange": null, "flip": null, "assist": null, "battle": false, "special": false}}}, "notes": 682, "latest": {"timestamp": "20260226-002005", "clear_type": {"value": "EXH-CLEAR", "new": true}, "dj_level": {"value": "AA", "new": true}, "score": {"value": 1170, "new": true}, "miss_count": {"value": 10, "new": true}, "options": {"arrange": null, "flip": null, "assist": null, "battle": false, "special": false}, "playspeed": null}, "achievement": {"fixed": {"clear_type": "EXH-CLEAR", "dj_level": "AA"}, "S-RANDOM": {"clear_type": null, "dj_level": null}, "fromhistoriesgenerate_lastversion": "0.21.dev6"}}}}