{"DP": {"HYPER": {"timestamps": [], "history": {}, "best": {"clear_type": {"value": "EXH-CLEAR", "timestamp": null, "options": null}, "dj_level": {"value": "A", "timestamp": null, "options": null}, "score": {"value": 1180, "timestamp": null, "options": null}, "miss_count": {"value": 11, "timestamp": null, "options": null}}}, "ANOTHER": {"timestamps": [], "history": {}, "best": {"clear_type": {"value": "CLEAR", "timestamp": null, "options": null}, "dj_level": {"value": "B", "timestamp": null, "options": null}, "score": {"value": 1552, "timestamp": null, "options": null}, "miss_count": {"value": 72, "timestamp": null, "options": null}}}}}