{"DP": {"HYPER": {"timestamps": [], "history": {}, "best": {"clear_type": {"value": "EXH-CLEAR", "timestamp": null, "options": null}, "dj_level": {"value": "AA", "timestamp": null, "options": null}, "score": {"value": 1725, "timestamp": null, "options": null}, "miss_count": {"value": 6, "timestamp": null, "options": null}}}, "NORMAL": {"timestamps": [], "history": {}, "best": {"clear_type": {"value": "NO PLAY", "timestamp": null, "options": null}, "score": {"value": 0, "timestamp": null, "options": null}}}, "ANOTHER": {"timestamps": ["20251224-002929", "20260214-163720", "20260215-155627", "20260307-171321"], "history": {"20251224-002929": {"clear_type": {"value": "FAILED", "new": false}, "dj_level": {"value": "A", "new": false}, "score": {"value": 2143, "new": false}, "miss_count": {"value": 82, "new": false}, "options": {"arrange": "MIR/OFF", "flip": null, "assist": null, "battle": false, "special": false}, "playspeed": null}, "20260214-163720": {"clear_type": {"value": "FAILED", "new": false}, "dj_level": {"value": "B", "new": false}, "score": {"value": 2049, "new": false}, "miss_count": {"value": 78, "new": true}, "options": {"arrange": "MIR/OFF", "flip": null, "assist": null, "battle": false, "special": false}, "playspeed": null}, "20260215-155627": {"clear_type": {"value": "FAILED", "new": false}, "dj_level": {"value": "A", "new": false}, "score": {"value": 2164, "new": false}, "miss_count": {"value": 68, "new": true}, "options": {"arrange": "MIR/OFF", "flip": null, "assist": null, "battle": false, "special": false}, "playspeed": null}, "20260307-171321": {"clear_type": {"value": "FAILED", "new": false}, "dj_level": {"value": "A", "new": false}, "score": {"value": 2115, "new": false}, "miss_count": {"value": 92, "new": false}, "options": {"arrange": "MIR/OFF", "flip": null, "assist": null, "battle": false, "special": false}, "playspeed": null}}, "best": {"latest": "20260307-171321", "clear_type": {"value": "E-CLEAR", "timestamp": null, "options": null}, "dj_level": {"value": "A", "timestamp": null, "options": null}, "score": {"value": 2181, "timestamp": null, "options": null}, "miss_count": {"value": 68, "timestamp": "20260215-155627", "options": {"arrange": "MIR/OFF", "flip": null, "assist": null, "battle": false, "special": false}}}, "notes": 1537, "latest": {"timestamp": "20260307-171321", "clear_type": {"value": "FAILED", "new": false}, "dj_level": {"value": "A", "new": false}, "score": {"value": 2115, "new": false}, "miss_count": {"value": 92, "new": false}, "options": {"arrange": "MIR/OFF", "flip": null, "assist": null, "battle": false, "special": false}, "playspeed": null}, "achievement": {"fixed": {"clear_type": "FAILED", "dj_level": "A"}, "S-RANDOM": {"clear_type": null, "dj_level": null}, "fromhistoriesgenerate_lastversion": "0.20.0"}}}}